VOEventLib/VOEvent.py
VOEventLib/Vutil.py
VOEventLib/__init__.py
VOEventLib-1.2.dist-info/DESCRIPTION.rst
VOEventLib-1.2.dist-info/METADATA
VOEventLib-1.2.dist-info/RECORD
VOEventLib-1.2.dist-info/WHEEL
VOEventLib-1.2.dist-info/metadata.json
VOEventLib-1.2.dist-info/top_level.txt
