Metadata-Version: 2.0
Name: VOEventLib
Version: 1.2
Summary: Python library to read, modify, and create VOEvents
Home-page: UNKNOWN
Author: Roy D. Williams
Author-email: roy.williams@ligo.org
Maintainer: Min-A Cho
Maintainer-email: min-a.cho@ligo.org
License: GNU General Public License Version 3
Platform: UNKNOWN
Classifier: Programming Language :: Python :: 3
Classifier: Operating System :: OS Independent
Classifier: Topic :: Internet
Classifier: Topic :: Scientific/Engineering :: Astronomy
Classifier: Topic :: Scientific/Engineering :: Physics
Requires-Python: >=3.5
